learning_verilog/bitwise_operators_tb.v
module bitwise_operators(
	// no inputs here 
);

reg [5:0] x = 0;        // 6bit variable
reg [5:0] y = 0;        // 6bit variable
reg [5:0] result = 0;   // 6bit variable

// Procedure used to continuously monitor 'x', 'y', and 'result'
initial begin
	$monitor("MON x=%b, y=%b, result=%b", x, y, result);
	$dumpfile("bitwise_operators_tb.vcd");
	$dumpvars(0,x,y,result);
end

// Procedure used to generate stimulus
initial begin
	#1;  // wait some time between examples
	x = 6'b00_0101;
	y = 6'b11_0001;
	result = x & y; // AND

	#1;  // Use the same values for x and y from above (reg stores the value)
	result = ~(x & y); // NAND Try: x ~& y to see what happens

	#1;
	x = 6'b10_0101;
	y = 6'b01_1011;
	result = x | y; // OR

	#1; 
	result = ~(x | y); // NOR Try: x ~| y to see what happens

	#1;
	x = 6'b01_0110;
	y = 6'b01_1011;
	result = x ^ y; // XOR

	#1; // NXOR is used to check if x = y
	result = x ~^ y; // NXOR

	#1
	x = y; // This should make all bits 1
	result = ~(x ^ y); // NXOR
end

endmodule

00_learning_verilog/bitwise_operators_tb.vcd
$date
	Thu Aug 22 23:37:22 2024
$end
$version
	Icarus Verilog
$end
$timescale
	1s
$end
$scope module bitwise_operators $end
$var reg 6 ! x [5:0] $end
$upscope $end
$scope module bitwise_operators $end
$var reg 6 " y [5:0] $end
$upscope $end
$scope module bitwise_operators $end
$var reg 6 # result [5:0] $end
$upscope $end
$enddefinitions $end
#0
$dumpvars
b0 #
b0 "
b0 !
$end
#1
b1 #
b110001 "
b101 !
#2
b111110 #
#3
b111111 #
b11011 "
b100101 !
#4
b0 #
#5
b1101 #
b10110 !
#6
b110010 #
#7
b111111 #
b11011 !
